kaldifeat-1.4.data/data/LICENSE
kaldifeat-1.4.data/data/README.md
kaldifeat-1.4.data/platlib/_kaldifeat.cpython-36m-x86_64-linux-gnu.so
kaldifeat-1.4.data/platlib/libkaldifeat_core.so
kaldifeat-1.4.data/platlib/kaldifeat/__init__.py
kaldifeat-1.4.data/platlib/kaldifeat/fbank.py
kaldifeat-1.4.data/platlib/kaldifeat/mfcc.py
kaldifeat-1.4.data/platlib/kaldifeat/offline_feature.py
kaldifeat-1.4.data/platlib/kaldifeat/plp.py
kaldifeat-1.4.data/platlib/kaldifeat/spectrogram.py
kaldifeat-1.4.dist-info/LICENSE
kaldifeat-1.4.dist-info/METADATA
kaldifeat-1.4.dist-info/WHEEL
kaldifeat-1.4.dist-info/top_level.txt
kaldifeat-1.4.dist-info/RECORD
