Metadata-Version: 2.1
Name: kaldifeat
Version: 1.4
Summary: UNKNOWN
Home-page: https://github.com/csukuangfj/kaldifeat
Author: Fangjun Kuang
Author-email: csukuangfj@gmail.com
License: Apache licensed, as found in the LICENSE file
Platform: UNKNOWN
Classifier: Programming Language :: C++
Classifier: Programming Language :: Python
Classifier: Programming Language :: Python :: 3
Classifier: Programming Language :: Python :: 3.6
Classifier: Programming Language :: Python :: 3.7
Classifier: Programming Language :: Python :: 3.8
Classifier: Topic :: Scientific/Engineering :: Artificial Intelligence
Requires-Python: >=3.6.0
Requires-Dist: torch (==1.8.1)
